{"Version":"1.0.0.0","LastState":11,"Modules":[{"ValidatedSteerId":1,"ValidatedDriveId":8,"ValidatedEncoderId":1,"IsEncoderOffsetConfigured":true,"IsDeviceSelectionCompleted":true,"IsConfigurationCompleted":true,"ModuleName":"Front Left","ModuleId":0,"Encoder":{"Id":1,"Name":"CANCoder vers. H (Device ID 1)","Model":"CANCoder vers. H","CANbus":"rio","CANbusFriendly":""},"SteerMotor":{"Id":1,"Name":"Talon FX vers. C (Device ID 1)","Model":"Talon FX vers. C","CANbus":"rio","CANbusFriendly":""},"DriveMotor":{"Id":8,"Name":"Talon FX vers. C (Device ID 8)","Model":"Talon FX vers. C","CANbus":"rio","CANbusFriendly":""},"IsSteerInverted":false,"EncoderOffset":-0.0498046875,"DriveMotorSelectionState":1,"SteerMotorSelectionState":1,"SteerEncoderSelectionState":1,"IsModuleValidationComplete":true},{"ValidatedSteerId":7,"ValidatedDriveId":6,"ValidatedEncoderId":4,"IsEncoderOffsetConfigured":true,"IsDeviceSelectionCompleted":true,"IsConfigurationCompleted":true,"ModuleName":"Front Right","ModuleId":1,"Encoder":{"Id":4,"Name":"CANCoder (Device ID 4)","Model":"CANCoder vers. H","CANbus":"rio","CANbusFriendly":""},"SteerMotor":{"Id":7,"Name":"Talon FX vers. C (Device ID 7)","Model":"Talon FX vers. C","CANbus":"rio","CANbusFriendly":""},"DriveMotor":{"Id":6,"Name":"Talon FX vers. C (Device ID 6)","Model":"Talon FX vers. C","CANbus":"rio","CANbusFriendly":""},"IsSteerInverted":false,"EncoderOffset":-0.238525390625,"DriveMotorSelectionState":1,"SteerMotorSelectionState":1,"SteerEncoderSelectionState":1,"IsModuleValidationComplete":true},{"ValidatedSteerId":3,"ValidatedDriveId":2,"ValidatedEncoderId":0,"IsEncoderOffsetConfigured":true,"IsDeviceSelectionCompleted":true,"IsConfigurationCompleted":true,"ModuleName":"Back Left","ModuleId":2,"Encoder":{"Id":0,"Name":"CANCoder vers. H (Device ID 0)","Model":"CANCoder vers. H","CANbus":"rio","CANbusFriendly":""},"SteerMotor":{"Id":3,"Name":"Talon FX vers. C (Device ID 3)","Model":"Talon FX vers. C","CANbus":"rio","CANbusFriendly":""},"DriveMotor":{"Id":2,"Name":"Talon FX vers. C (Device ID 2)","Model":"Talon FX vers. C","CANbus":"rio","CANbusFriendly":""},"IsSteerInverted":false,"EncoderOffset":-0.13232421875,"DriveMotorSelectionState":1,"SteerMotorSelectionState":1,"SteerEncoderSelectionState":1,"IsModuleValidationComplete":true},{"ValidatedSteerId":5,"ValidatedDriveId":4,"ValidatedEncoderId":3,"IsEncoderOffsetConfigured":true,"IsDeviceSelectionCompleted":true,"IsConfigurationCompleted":true,"ModuleName":"Back Right","ModuleId":3,"Encoder":{"Id":3,"Name":"CANCoder vers. H (Device ID 3)","Model":"CANCoder vers. H","CANbus":"rio","CANbusFriendly":""},"SteerMotor":{"Id":5,"Name":"Talon FX vers. C (Device ID 5)","Model":"Talon FX vers. C","CANbus":"rio","CANbusFriendly":""},"DriveMotor":{"Id":4,"Name":"Talon FX vers. C (Device ID 4)","Model":"Talon FX vers. C","CANbus":"rio","CANbusFriendly":""},"IsSteerInverted":false,"EncoderOffset":-0.19287109375,"DriveMotorSelectionState":1,"SteerMotorSelectionState":1,"SteerEncoderSelectionState":1,"IsModuleValidationComplete":true}],"SwerveOptions":{"IsValidConfiguration":true,"Gyro":{"Id":13,"Name":"Pigeon 2 (Device ID 13)","Model":"Pigeon 2","CANbus":"rio","CANbusFriendly":""},"IsValidGyroCANbus":true,"VerticalTrackSizeInches":21.0,"HorizontalTrackSizeInches":21.0,"WheelRadiusInches":4.0,"IsLeftSideInverted":false,"IsRightSideInverted":true,"SwerveModuleType":4,"SwerveModuleConfiguration":{"_CouplingRatio":3.5714285714285716,"_CustomName":"L3","SteerRatio":21.428571428571427,"Flipped":4,"DriveRatio":6.122448979591837,"CouplingRatio":3.5714285714285716,"CustomName":"L3"},"HasVerifiedSteer":true,"HasVerifiedDrive":true}}